example_pkg/__init__.py
example_pkg_matkoniecz/__init__.py
leafleter/__init__.py
leafleter/generator.py
leafleter-0.1.9.dist-info/LICENSE
leafleter-0.1.9.dist-info/METADATA
leafleter-0.1.9.dist-info/WHEEL
leafleter-0.1.9.dist-info/top_level.txt
leafleter-0.1.9.dist-info/RECORD
