Metadata-Version: 2.1
Name: leafleter
Version: 0.1.9
Summary: Helper script to generate leaflet map websites.
Home-page: https://github.com/matkoniecz/leafleter_python
Author: Mateusz Konieczny
Author-email: matkoniecz@tutanota.com
License: UNKNOWN
Platform: UNKNOWN
Classifier: Programming Language :: Python :: 3
Classifier: License :: OSI Approved :: MIT License
Classifier: Operating System :: OS Independent
